dmSQLAlchemy/__init__.py
dmSQLAlchemy/base.py
dmSQLAlchemy/dmPython.py
dmSQLAlchemy/json.py
dmSQLAlchemy/types.py
sqlalchemy_dm_main-1.4.41.dist-info/licenses/LICENSE
sqlalchemy_dm_main-1.4.41.dist-info/METADATA
sqlalchemy_dm_main-1.4.41.dist-info/WHEEL
sqlalchemy_dm_main-1.4.41.dist-info/entry_points.txt
sqlalchemy_dm_main-1.4.41.dist-info/top_level.txt
sqlalchemy_dm_main-1.4.41.dist-info/RECORD
