Metadata-Version: 2.4
Name: SQLAlchemy-dm-main
Version: 1.4.41
Summary: SQLAlchemy dialect for DM
Author: Dameng
Author-email: 
Keywords: DM SQLAlchemy
License-File: LICENSE
Requires-Dist: dmPython
Requires-Dist: sqlalchemy<2.0,>1.3.24
Dynamic: author
Dynamic: keywords
Dynamic: license-file
Dynamic: requires-dist
Dynamic: summary
